Blaeu.py
EXAMPLES.md
LICENCE
MANIFEST.in
README.md
README.rst
TAGS
blaeu-cert
blaeu-http
blaeu-ntp
blaeu-reach
blaeu-resolve
blaeu-traceroute
setup.py
blaeu.egg-info/PKG-INFO
blaeu.egg-info/SOURCES.txt
blaeu.egg-info/dependency_links.txt
blaeu.egg-info/requires.txt
blaeu.egg-info/top_level.txt