Metadata-Version: 2.1
Name: blaeu
Version: 2.2
Summary: Tools to create (and analyze) RIPE Atlas network measurements
Home-page: https://framagit.org/bortzmeyer/blaeu
Author: Stéphane Bortzmeyer
Author-email: stephane+frama@bortzmeyer.org
License: BSD
Keywords: networking ripe atlas monitoring ip ping traceroute dig dns
Classifier: Development Status :: 5 - Production/Stable
Classifier: Intended Audience :: System Administrators
Classifier: Intended Audience :: Telecommunications Industry
Classifier: Topic :: System :: Networking
Classifier: License :: OSI Approved :: MIT License
Classifier: Programming Language :: Python :: 3
Requires-Python: >=3
Provides-Extra: dev
License-File: LICENCE
